{"id": 1192, "title": [{"mbid": "2d20806c-95f7-4b01-8f01-539174fd0614", "name": "天国と地獄", "type": "work"}], "artist": [{"mbid": "265a2fb6-dde5-48d3-9e6e-47708aa5e10a", "name": "UNISON SQUARE GARDEN", "type": "artist"}], "song_instances": [{"video_id": "I0pRu6XehDA", "timestamp_start": "01:48:44", "timestamp_end": null}, {"video_id": "IFwX-CLZroY", "timestamp_start": "01:36:01", "timestamp_end": null}, {"video_id": "j4X21zaA58E", "timestamp_start": "00:54:35", "timestamp_end": null}, {"video_id": "JGy2S8i6DIE", "timestamp_start": "01:28:01", "timestamp_end": null}, {"video_id": "oJMOPirPsdg", "timestamp_start": "00:32:17", "timestamp_end": null}, {"video_id": "OkW95gQH_to", "timestamp_start": "00:53:06", "timestamp_end": null}, {"video_id": "Q_R88JxygoM", "timestamp_start": "01:12:28", "timestamp_end": null}, {"video_id": "XQOY5LqucVs", "timestamp_start": "00:11:16", "timestamp_end": null}, {"video_id": "pK_6_FJ-TMs", "timestamp_start": "01:13:34", "timestamp_end": null}]}