{"id": 304, "title": [{"mbid": "79e3acff-0202-4432-a5bd-a3ba18ccafb3", "name": "明日への扉", "type": "work"}], "artist": [{"mbid": "b9523552-8d2c-44c0-9e38-2d7920b8e380", "name": "I WiSH", "type": "artist"}], "song_instances": [{"video_id": "1uIx1hiWlBQ", "timestamp_start": "00:48:46", "timestamp_end": null}, {"video_id": "45cFAXNbRRQ", "timestamp_start": "01:26:30", "timestamp_end": null}, {"video_id": "aI0u8rK7mFM", "timestamp_start": "01:53:30", "timestamp_end": null}, {"video_id": "h5zxFnJdUfk", "timestamp_start": "01:56:37", "timestamp_end": null}, {"video_id": "lkyQ5qXPzo4", "timestamp_start": "00:51:02", "timestamp_end": null}, {"video_id": "vX9PoR5a8-M", "timestamp_start": "01:24:58", "timestamp_end": null}, {"video_id": "vXblVT1jeVs", "timestamp_start": "01:00:25", "timestamp_end": null}, {"video_id": "wNmD32lLhXk", "timestamp_start": "02:19:43", "timestamp_end": null}, {"video_id": "wWC09LdmpeU", "timestamp_start": "01:04:18", "timestamp_end": null}]}