{"id": 33, "title": [{"mbid": "5e035201-9e23-4bdf-a6f8-b3757d2a6fa5", "name": "まどろみの約束", "type": "work"}], "artist": [{"mbid": "756cf20c-eaa1-428a-b70d-53571b8c83df", "name": "伊原摩耶花", "type": "artist"}, {"mbid": "84a561be-363a-4859-8c1b-48d893108bfe", "name": "佐藤聡美", "type": "artist"}, {"mbid": "d9bcb30e-a9d1-4e65-b1eb-bb2709376b51", "name": "千反田える", "type": "artist"}, {"mbid": "f74f5468-91f9-443b-aedc-c969a75d1678", "name": "茅野愛衣", "type": "artist"}], "song_instances": [{"video_id": "-IedogNpTEc", "timestamp_start": "00:18:45", "timestamp_end": null}, {"video_id": "1_qp21q1YbU", "timestamp_start": "00:51:36", "timestamp_end": null}, {"video_id": "8kRksvpcD7Q", "timestamp_start": "01:22:56", "timestamp_end": null}, {"video_id": "fcR3UbqjkNY", "timestamp_start": "00:15:55", "timestamp_end": null}, {"video_id": "PZiU3gNOABs", "timestamp_start": "01:21:27", "timestamp_end": null}, {"video_id": "RHuOJ2s9pwI", "timestamp_start": "00:22:51", "timestamp_end": null}, {"video_id": "Rsse_N8m1fQ", "timestamp_start": "01:56:40", "timestamp_end": null}]}