{"id": 427, "title": [{"mbid": "ad1b10a8-bcdd-3de5-abb2-5b7e5e6e00b6", "name": "夢をかなえてドラえもん", "type": "work"}], "artist": [{"mbid": "38d589dc-b9c7-4e94-b98e-f392f41bbe6e", "name": "mao", "type": "artist"}], "song_instances": [{"video_id": "3Og5-9s1rK0", "timestamp_start": "00:45:42", "timestamp_end": null}, {"video_id": "DkWKrvpwgBY", "timestamp_start": "01:45:13", "timestamp_end": null}, {"video_id": "mUboYaIy9fE", "timestamp_start": "00:37:35", "timestamp_end": null}, {"video_id": "vFvfmmszv5g", "timestamp_start": "00:13:39", "timestamp_end": null}]}