{"id": 454, "title": [{"mbid": "97359fa9-8237-45cc-a2f3-007ee8f85d86", "name": "ロマンスの神様", "type": "work"}], "artist": [{"mbid": "3597f215-1cc1-4395-97e5-c64cdae51ca1", "name": "広瀬香美", "type": "artist"}], "song_instances": [{"video_id": "3sv2VlJ3Njo", "timestamp_start": "01:48:43", "timestamp_end": null}, {"video_id": "5BZLQlgfMCw", "timestamp_start": "01:01:31", "timestamp_end": null}, {"video_id": "5RvKDC7Q4x8", "timestamp_start": "01:39:06", "timestamp_end": null}, {"video_id": "Bgdde9dxlQs", "timestamp_start": "00:14:00", "timestamp_end": null}, {"video_id": "dzQ6gLH7rUs", "timestamp_start": "01:15:14", "timestamp_end": null}, {"video_id": "ImgBMnRTiRY", "timestamp_start": "01:12:35", "timestamp_end": null}, {"video_id": "Imjs-Dlwn6M", "timestamp_start": "00:54:51", "timestamp_end": null}, {"video_id": "jBCRcmBEIFc", "timestamp_start": "01:16:24", "timestamp_end": null}, {"video_id": "jEMGeGtn_wE", "timestamp_start": "01:30:07", "timestamp_end": null}, {"video_id": "JxIVyYFaXok", "timestamp_start": "02:58:57", "timestamp_end": null}, {"video_id": "Kp1uhYG6lwc", "timestamp_start": "01:56:00", "timestamp_end": null}, {"video_id": "MrOxb3Gfr-Y", "timestamp_start": "00:44:58", "timestamp_end": null}, {"video_id": "nVXZNXgAKMQ", "timestamp_start": "01:27:06", "timestamp_end": null}, {"video_id": "PZUS9DLQ6oM", "timestamp_start": "01:37:35", "timestamp_end": null}, {"video_id": "RUMggdycPXs", "timestamp_start": "00:42:26", "timestamp_end": null}, {"video_id": "wjPYIworZP4", "timestamp_start": "00:59:27", "timestamp_end": null}, {"video_id": "wNmD32lLhXk", "timestamp_start": "01:16:17", "timestamp_end": null}, {"video_id": "zcEOWTiBBQA", "timestamp_start": "01:38:08", "timestamp_end": null}]}