{"id": 663, "title": [{"mbid": "b74a0fd7-b18d-46b0-b95b-aedc6aecdf8e", "name": "Komm, Susser Tod ～甘き死よ、来たれ～", "type": "recording"}], "artist": [{"mbid": "3d796c64-4fc5-4112-9f6b-edc64dd571c8", "name": "ARIANNE", "type": "artist"}], "song_instances": [{"video_id": "6-fXz8KcaeQ", "timestamp_start": "00:12:45", "timestamp_end": null}, {"video_id": "7r_iHzDfBro", "timestamp_start": "00:41:02", "timestamp_end": null}, {"video_id": "BQGIKqvq6O8", "timestamp_start": "01:14:55", "timestamp_end": null}, {"video_id": "qdmBWlbzQN0", "timestamp_start": "01:04:28", "timestamp_end": null}, {"video_id": "xokwQ0RVYGk", "timestamp_start": "00:20:08", "timestamp_end": null}, {"video_id": "Znp4s7Vq2q4", "timestamp_start": "03:04:57", "timestamp_end": null}]}