{"id": 706, "title": [{"name": "バトルフロンティア"}, {"name": "Battle Frontier"}], "artist": [{"name": "高屋亜希那"}], "song_instances": [{"video_id": "6RzPLhgeLCA", "timestamp_start": "00:54:27", "timestamp_end": null}, {"video_id": "DVbAljOTJ2k", "timestamp_start": "01:09:38", "timestamp_end": null}, {"video_id": "GDcNHOb9z1U", "timestamp_start": "01:05:58", "timestamp_end": null}, {"video_id": "JZGfTHFIUvE", "timestamp_start": "01:25:20", "timestamp_end": null}, {"video_id": "myw7-7gDjJ4", "timestamp_start": "01:19:37", "timestamp_end": null}, {"video_id": "p3WjY25PYWM", "timestamp_start": "01:17:51", "timestamp_end": null}, {"video_id": "pxCtZeLQF-s", "timestamp_start": "01:17:01", "timestamp_end": null}, {"video_id": "TktL7_q29Ak", "timestamp_start": "00:22:43", "timestamp_end": null}, {"video_id": "v7osiVwnfzs", "timestamp_start": "00:50:28", "timestamp_end": null}, {"video_id": "vz5YS98PQ0k", "timestamp_start": "00:27:32", "timestamp_end": null}, {"video_id": "wwC3IQPQImI", "timestamp_start": "00:26:59", "timestamp_end": null}, {"video_id": "xSouPEt3L3w", "timestamp_start": "00:57:47", "timestamp_end": null}, {"video_id": "_RyIzJokRGc", "timestamp_start": "00:32:40", "timestamp_end": null}]}