{"id": 750, "title": [{"name": "- LEGNE - 仇なす剣 光の旋律"}, {"name": "- LEGNE - Adanasu Ken Hikari no Senritsu"}, {"name": "-LEGNE- 仇なす剣 光の旋律"}], "artist": [{"mbid": "35689a4a-64b3-463f-909c-127998c65ebc", "name": "Rosenburg Engel", "type": "artist"}], "song_instances": [{"video_id": "74Ft6V6GPWw", "timestamp_start": "01:32:46", "timestamp_end": null}, {"video_id": "AjpEbraDcYc", "timestamp_start": "00:52:54", "timestamp_end": null}, {"video_id": "GAt-okIwGZg", "timestamp_start": "01:13:23", "timestamp_end": null}, {"video_id": "J6qtalD5SUQ", "timestamp_start": "00:27:58", "timestamp_end": null}, {"video_id": "myw7-7gDjJ4", "timestamp_start": "04:25:44", "timestamp_end": null}, {"video_id": "PZiU3gNOABs", "timestamp_start": "00:22:46", "timestamp_end": null}, {"video_id": "_N_iKeFuY8g", "timestamp_start": "00:20:49", "timestamp_end": null}]}