{"id": 761, "title": [{"mbid": "5e3ddba4-a0c2-43b1-ab9e-4704fdc65764", "name": "聖少女領域", "type": "work"}], "artist": [{"mbid": "12b6e407-4ec0-4cc6-80d4-b38d7df99694", "name": "ALI PROJECT", "type": "artist"}], "song_instances": [{"video_id": "7ouSFAiyIS0", "timestamp_start": "00:42:52", "timestamp_end": null}, {"video_id": "7zN9RkszNow", "timestamp_start": "00:48:48", "timestamp_end": null}, {"video_id": "NrcaPkrgBqU", "timestamp_start": "03:11:41", "timestamp_end": null}, {"video_id": "YaPmQ8Uvdxk", "timestamp_start": "01:14:46", "timestamp_end": null}]}