{"id": 801, "title": [{"mbid": "4baab936-8929-45e9-ab21-82ed377e33bc", "name": "LADY CRAZY", "type": "work"}], "artist": [{"mbid": "c2deade3-c5e4-4061-8c13-9bd8f53a143b", "name": "HIMEHINA", "type": "artist"}], "song_instances": [{"video_id": "7zN9RkszNow", "timestamp_start": "02:08:51", "timestamp_end": null}, {"video_id": "beUUCfZEGXw", "timestamp_start": "02:19:01", "timestamp_end": null}, {"video_id": "h0I316pABP0", "timestamp_start": "00:02:58", "timestamp_end": null}, {"video_id": "i_tTiRAbh9c", "timestamp_start": "01:11:06", "timestamp_end": null}, {"video_id": "kdR_DwmN2EE", "timestamp_start": "00:07:31", "timestamp_end": null}, {"video_id": "ZBiBOtP6SXw", "timestamp_start": "02:05:06", "timestamp_end": null}]}