{"id": 834, "title": [{"name": "ゆめいっぱい"}, {"name": "Yume Ippai"}], "artist": [{"mbid": "1a28a6a6-5e61-4c1c-8a60-a24bd8d3c030", "name": "関ゆみ子", "type": "artist"}], "song_instances": [{"video_id": "9m05n0eWWrQ", "timestamp_start": "01:58:42", "timestamp_end": null}, {"video_id": "d7C_w10N_jg", "timestamp_start": "00:16:29", "timestamp_end": null}, {"video_id": "G2LiOcTi2i8", "timestamp_start": "00:42:51", "timestamp_end": null}, {"video_id": "H6tU3OJnbbQ", "timestamp_start": "00:11:00", "timestamp_end": null}, {"video_id": "Ix7xUL6S8no", "timestamp_start": "00:57:15", "timestamp_end": null}, {"video_id": "J8AmhJ_hT84", "timestamp_start": "01:54:14", "timestamp_end": null}, {"video_id": "mUboYaIy9fE", "timestamp_start": "00:42:24", "timestamp_end": null}, {"video_id": "P_InWNu4qU8", "timestamp_start": "01:04:57", "timestamp_end": null}, {"video_id": "Tn6LDK1zeoE", "timestamp_start": "00:58:25", "timestamp_end": null}, {"video_id": "v7osiVwnfzs", "timestamp_start": "00:37:58", "timestamp_end": null}, {"video_id": "vFvfmmszv5g", "timestamp_start": "00:21:39", "timestamp_end": null}]}