{"id": "9_qQaYvk_So", "title": "【歌枠】アニソン封印！⚡️JPOP歌枠💎 #ウタノライブ【#KARAOKE/ #Vsinger】", "thumbnails": {"default": {"url": "https://i.ytimg.com/vi/9_qQaYvk_So/default.jpg", "width": 120, "height": 90}, "medium": {"url": "https://i.ytimg.com/vi/9_qQaYvk_So/mqdefault.jpg", "width": 320, "height": 180}, "high": {"url": "https://i.ytimg.com/vi/9_qQaYvk_So/hqdefault.jpg", "width": 480, "height": 360}, "standard": {"url": "https://i.ytimg.com/vi/9_qQaYvk_So/sddefault.jpg", "width": 640, "height": 480}, "maxres": {"url": "https://i.ytimg.com/vi/9_qQaYvk_So/maxresdefault.jpg", "width": 1280, "height": 720}}, "publishedAt": "2023-06-23T12:15:15Z", "setlist": [{"id": 607, "title": [{"mbid": "3c61b60e-10c7-4ba6-a467-e08732eef71f", "name": "promise", "type": "work"}], "artist": [{"mbid": "3597f215-1cc1-4395-97e5-c64cdae51ca1", "name": "広瀬香美", "type": "artist"}], "timestamp_start": "00:05:29", "timestamp_end": null}, {"id": 675, "title": [{"mbid": "f9087733-dc96-4364-bc1b-8866885bd37b", "name": "逢いたくていま", "type": "work"}], "artist": [{"mbid": "c15576a7-48dd-4916-a3b7-e31c9824f36c", "name": "MISIA", "type": "artist"}], "timestamp_start": "00:12:00", "timestamp_end": null}, {"id": 303, "title": [{"mbid": "9d4558da-208a-3a35-a685-2892c6b7ddc3", "name": "First Love", "type": "work"}], "artist": [{"mbid": "b539e453-c4fe-47e3-8a07-8517eac74429", "name": "宇多田ヒカル", "type": "artist"}], "timestamp_start": "00:17:52", "timestamp_end": null}, {"id": 876, "title": [{"mbid": "2cef19ed-a903-4fd9-bd74-99ef3a58e85a", "name": "Flavor Of Life", "type": "work"}], "artist": [{"mbid": "b539e453-c4fe-47e3-8a07-8517eac74429", "name": "宇多田ヒカル", "type": "artist"}], "timestamp_start": "00:23:12", "timestamp_end": null}, {"id": 317, "title": [{"mbid": "82da63bd-128c-31d1-9183-d7bdf440eea2", "name": "GLAMOROUS SKY", "type": "work"}], "artist": [{"mbid": "f8d6e5df-069e-4b8d-9a13-cc7e0a558dd1", "name": "中島美嘉", "type": "artist"}], "timestamp_start": "00:28:43", "timestamp_end": null}, {"id": 877, "title": [{"mbid": "cf0c5de1-ac43-46cf-9e5b-097efc5d6434", "name": "LIFE", "type": "work"}], "artist": [{"mbid": "f8d6e5df-069e-4b8d-9a13-cc7e0a558dd1", "name": "中島美嘉", "type": "artist"}], "timestamp_start": "00:33:06", "timestamp_end": null}, {"id": 298, "title": [{"mbid": "d4909652-41f8-41fa-9ff9-2aeedee4923b", "name": "DEAR MY FRIEND", "type": "work"}], "artist": [{"mbid": "acf20c38-8a14-4406-9039-fe78d26c2e4e", "name": "Every Little Thing", "type": "artist"}], "timestamp_start": "00:40:49", "timestamp_end": null}, {"id": 439, "title": [{"mbid": "df1cb327-e029-4904-a5d8-5faa2f499620", "name": "出逢った頃のように", "type": "work"}], "artist": [{"mbid": "acf20c38-8a14-4406-9039-fe78d26c2e4e", "name": "Every Little Thing", "type": "artist"}], "timestamp_start": "00:44:33", "timestamp_end": null}, {"id": 570, "title": [{"mbid": "43698488-7cd4-463c-8641-47c17d2914bc", "name": "大阪LOVER", "type": "work"}], "artist": [{"mbid": "f984ebbf-8534-4163-9cb8-295c91535446", "name": "DREAMS COME TRUE", "type": "artist"}], "timestamp_start": "00:52:25", "timestamp_end": null}, {"id": 443, "title": [{"mbid": "3a900872-9287-4f08-bf32-4e4aceb5e840", "name": "やさしいキスをして", "type": "work"}], "artist": [{"mbid": "f984ebbf-8534-4163-9cb8-295c91535446", "name": "DREAMS COME TRUE", "type": "artist"}], "timestamp_start": "01:04:22", "timestamp_end": null}, {"id": 564, "title": [{"mbid": "c364287a-d30a-45e8-8962-a0031a22df4c", "name": "Main Title", "type": "recording"}], "artist": [{"mbid": "d1520a68-cad6-4bc3-9b02-dc19671a0a29", "name": "佐藤惣之助", "type": "artist"}, {"mbid": "fa048f1b-ef64-45b7-a17c-d546fcbe14a2", "name": "古関裕而", "type": "artist"}], "timestamp_start": "01:07:45", "timestamp_end": null}, {"id": 309, "title": [{"mbid": "c38174b3-1c0e-416c-a19e-0ec9e111bacb", "name": "茜色の約束", "type": "work"}], "artist": [{"mbid": "18191eea-369f-42e8-96ab-c1c24e4d0011", "name": "いきものがかり", "type": "artist"}], "timestamp_start": "01:14:33", "timestamp_end": null}, {"id": 878, "title": [{"mbid": "64f0e371-179c-4e2c-a55b-22fcf1f274e2", "name": "かばん", "type": "recording"}], "artist": [{"mbid": "53e90c12-6ad0-4d1e-ad5b-f2e5d0059946", "name": "aiko", "type": "artist"}], "timestamp_start": "01:19:38", "timestamp_end": null}, {"id": 255, "title": [{"mbid": "b9da6175-0fed-4ed5-8b4d-3edf28b247f1", "name": "心という名の不可解", "type": "work"}], "artist": [{"mbid": "e134b52f-2e9e-4734-9bc3-bea9648d1fa1", "name": "Ado", "type": "artist"}], "timestamp_start": "01:24:45", "timestamp_end": null}, {"id": 245, "title": [{"mbid": "7f15cbe6-d32c-4c97-95ca-848bed0fe638", "name": "阿修羅ちゃん", "type": "work"}], "artist": [{"mbid": "e134b52f-2e9e-4734-9bc3-bea9648d1fa1", "name": "Ado", "type": "artist"}], "timestamp_start": "01:29:15", "timestamp_end": null}, {"id": 246, "title": [{"mbid": "fc842ef1-bea8-4894-93b7-a0caac1c3fb2", "name": "踊", "type": "work"}], "artist": [{"mbid": "e134b52f-2e9e-4734-9bc3-bea9648d1fa1", "name": "Ado", "type": "artist"}], "timestamp_start": "01:32:40", "timestamp_end": null}, {"id": 244, "title": [{"mbid": "58a9cf57-e8a5-4743-bc65-56d70922519a", "name": "レディメイド", "type": "work"}], "artist": [{"mbid": "e134b52f-2e9e-4734-9bc3-bea9648d1fa1", "name": "Ado", "type": "artist"}], "timestamp_start": "01:36:18", "timestamp_end": null}, {"id": 551, "title": [{"mbid": "a99dd10e-ba27-4ee7-8bfc-838153062688", "name": "Pretender", "type": "work"}], "artist": [{"mbid": "6dddd7a2-5583-49d0-a8b2-9ee46d04f27e", "name": "Official髭男dism", "type": "artist"}], "timestamp_start": "01:41:47", "timestamp_end": null}, {"id": 678, "title": [{"mbid": "a5923691-723e-4425-adc6-600c07916ecc", "name": "Cinderella Boy", "type": "recording"}], "artist": [{"mbid": "76c63dd7-96d1-42d9-a596-4d576a464008", "name": "Saucy Dog", "type": "artist"}], "timestamp_start": "01:47:06", "timestamp_end": null}, {"id": 535, "title": [{"mbid": "832ef375-5b0a-4914-8303-f7e1a4c92ac4", "name": "ベテルギウス", "type": "work"}], "artist": [{"mbid": "4337f1a5-9e02-4b46-98c3-e3c28683a9b5", "name": "優里", "type": "artist"}], "timestamp_start": "01:50:50", "timestamp_end": null}]}