{"id": "g-IEkPEs5-I", "title": "【歌枠】超かっこいいレトラちゃんと歌う🎤⚡️ #れとらぶ #ヴイアラ #ウタノライブ 【KARAOKE/Vsinger】", "thumbnails": {"default": {"url": "https://i.ytimg.com/vi/g-IEkPEs5-I/default.jpg", "width": 120, "height": 90}, "medium": {"url": "https://i.ytimg.com/vi/g-IEkPEs5-I/mqdefault.jpg", "width": 320, "height": 180}, "high": {"url": "https://i.ytimg.com/vi/g-IEkPEs5-I/hqdefault.jpg", "width": 480, "height": 360}, "standard": {"url": "https://i.ytimg.com/vi/g-IEkPEs5-I/sddefault.jpg", "width": 640, "height": 480}, "maxres": {"url": "https://i.ytimg.com/vi/g-IEkPEs5-I/maxresdefault.jpg", "width": 1280, "height": 720}}, "publishedAt": "2025-05-15T12:19:49Z", "setlist": [{"id": 124, "title": [{"mbid": "cc846930-fb15-45ee-a507-be86f7fda159", "name": "ADAMAS", "type": "work"}], "artist": [{"mbid": "85d76093-9865-4605-97fa-8c910929d366", "name": "LiSA", "type": "artist"}], "timestamp_start": "00:02:58", "timestamp_end": null}, {"id": 112, "title": [{"mbid": "ffb74439-604b-4280-867f-7588d322dfaf", "name": "ラピスラズリ", "type": "work"}], "artist": [{"mbid": "9e190e5d-3612-43c6-9381-d4972efca5c3", "name": "藍井エイル", "type": "artist"}], "timestamp_start": "00:11:25", "timestamp_end": null}, {"id": 908, "title": [{"mbid": "fe442eb1-c6e4-4598-817b-8b70c355d9b0", "name": "Another Rampage", "type": "work"}], "artist": [{"mbid": "d3305a01-ed26-4e6c-89a7-a57aa2901c9f", "name": "ストレイライト", "type": "artist"}], "timestamp_start": "00:22:13", "timestamp_end": null}, {"id": 478, "title": [{"mbid": "0a2ddda3-f83e-4a3b-86e4-3023c8b8c0f3", "name": "Departures 〜あなたにおくるアイの歌〜", "type": "work"}], "artist": [{"mbid": "fb483f0a-d1ec-4a98-8237-0b1d7542aca7", "name": "EGOIST", "type": "artist"}], "timestamp_start": "00:26:57", "timestamp_end": null}, {"id": 253, "title": [{"mbid": "feec526f-e200-4136-9fdd-60f09c4d60ba", "name": "風のゆくえ", "type": "work"}], "artist": [{"mbid": "e134b52f-2e9e-4734-9bc3-bea9648d1fa1", "name": "Ado", "type": "artist"}], "timestamp_start": "00:33:37", "timestamp_end": null}, {"id": 136, "title": [{"mbid": "d62b99a4-fc94-4753-be7d-c3c4212466d8", "name": "IGNITE", "type": "work"}], "artist": [{"mbid": "9e190e5d-3612-43c6-9381-d4972efca5c3", "name": "藍井エイル", "type": "artist"}], "timestamp_start": "00:47:44", "timestamp_end": null}, {"id": 349, "title": [{"mbid": "9af15d33-c57b-48fb-a97c-d6cfc5830540", "name": "主人公になれるはずのストーリー", "type": "recording"}], "artist": [{"mbid": "2bc6510c-88d4-454e-a00e-0f127acd7787", "name": "白玖ウタノ", "type": "artist"}], "timestamp_start": "00:55:07", "timestamp_end": null}]}