{"id": "RX9HWLtPDMA", "title": "【歌枠】ぬいぬいと久しぶりの歌枠💗   #ウタぬい 【KARAOKE/Vsinger】", "thumbnails": {"default": {"url": "https://i.ytimg.com/vi/RX9HWLtPDMA/default.jpg", "width": 120, "height": 90}, "medium": {"url": "https://i.ytimg.com/vi/RX9HWLtPDMA/mqdefault.jpg", "width": 320, "height": 180}, "high": {"url": "https://i.ytimg.com/vi/RX9HWLtPDMA/hqdefault.jpg", "width": 480, "height": 360}, "standard": {"url": "https://i.ytimg.com/vi/RX9HWLtPDMA/sddefault.jpg", "width": 640, "height": 480}, "maxres": {"url": "https://i.ytimg.com/vi/RX9HWLtPDMA/maxresdefault.jpg", "width": 1280, "height": 720}}, "publishedAt": "2024-11-22T12:21:36Z", "setlist": [{"id": 63, "title": [{"mbid": "cccfd6d8-6be4-439f-a6da-0636054c6f5f", "name": "君色シグナル", "type": "work"}], "artist": [{"mbid": "fe9532d4-3f0e-4685-bce6-92f91fdb35a0", "name": "春奈るな", "type": "artist"}], "timestamp_start": "00:08:40", "timestamp_end": null}, {"id": 197, "title": [{"mbid": "137109e6-bdfb-405f-bd2f-440b30698af3", "name": "ルンがピカッと光ったら", "type": "work"}], "artist": [{"mbid": "eec83a8c-4698-43d6-a62c-abed00e7e6b5", "name": "ワルキューレ", "type": "artist"}], "timestamp_start": "00:19:37", "timestamp_end": null}, {"id": 42, "title": [{"mbid": "f735dffe-0a2c-4436-b0c3-a3cfc4667aa1", "name": "ココロのちず", "type": "work"}], "artist": [{"mbid": "81dd2f2e-4b60-40cf-8f51-18ced1ef78eb", "name": "BOYSTYLE", "type": "artist"}], "timestamp_start": "00:30:36", "timestamp_end": null}, {"id": 426, "title": [{"mbid": "36a27b29-009a-4779-8720-ae23eefed057", "name": "YUME日和", "type": "work"}], "artist": [{"mbid": "ee4c184e-90a5-44a6-b876-e692bb5d9a7e", "name": "島谷ひとみ", "type": "artist"}], "timestamp_start": "00:35:05", "timestamp_end": null}, {"id": 1090, "title": [{"mbid": "d8305377-a022-455e-8ea0-c21e8cf9bde7", "name": "ヒトリゴト", "type": "work"}], "artist": [{"mbid": "f3688ad9-cd14-4cee-8fa0-0f4434e762bb", "name": "ClariS", "type": "artist"}], "timestamp_start": "00:42:24", "timestamp_end": null}, {"id": 218, "title": [{"mbid": "7684e19d-0087-3897-9474-6394bc2d7d15", "name": "Lost my music", "type": "work"}], "artist": [{"mbid": "8ce84262-ce7b-48c7-9a29-637eedf5ebfb", "name": "涼宮ハルヒ", "type": "artist"}], "timestamp_start": "00:53:21", "timestamp_end": null}]}