{"id": "utou2uOtnk4", "title": "【ギター練習】ふわふわ時間歌いながら演奏するまで!!☁️ ＃ウタノライブ 【Vtuber/Vsinger】", "thumbnails": {"default": {"url": "https://i.ytimg.com/vi/utou2uOtnk4/default.jpg", "width": 120, "height": 90}, "medium": {"url": "https://i.ytimg.com/vi/utou2uOtnk4/mqdefault.jpg", "width": 320, "height": 180}, "high": {"url": "https://i.ytimg.com/vi/utou2uOtnk4/hqdefault.jpg", "width": 480, "height": 360}, "standard": {"url": "https://i.ytimg.com/vi/utou2uOtnk4/sddefault.jpg", "width": 640, "height": 480}, "maxres": {"url": "https://i.ytimg.com/vi/utou2uOtnk4/maxresdefault.jpg", "width": 1280, "height": 720}}, "publishedAt": "2024-09-04T12:12:58Z", "setlist": [{"id": 1439, "title": [{"name": "Don’t say “lazy”"}], "artist": [], "timestamp_start": "01:26:33", "timestamp_end": null}, {"id": 807, "title": [{"mbid": "b9aa4282-9de4-3a44-9f6b-baaeb3e0fcbb", "name": "ふわふわ時間", "type": "work"}], "artist": [{"mbid": "9ac83e0c-6a90-41cf-b06f-527ed0a79ffe", "name": "放課後ティータイム", "type": "artist"}], "timestamp_start": "01:34:50", "timestamp_end": null}]}